xialib_gcp/__init__.py
xialib_gcp/adaptors/__init__.py
xialib_gcp/adaptors/bigquery_adaptor.py
xialib_gcp/archivers/__init__.py
xialib_gcp/archivers/gcs_list_archiver.py
xialib_gcp/depositors/__init__.py
xialib_gcp/depositors/firestore_depositor.py
xialib_gcp/publishers/__init__.py
xialib_gcp/publishers/pubsub_publisher.py
xialib_gcp/storers/__init__.py
xialib_gcp/storers/gcs_storer.py
xialib_gcp/subscribers/__init__.py
xialib_gcp/subscribers/pubsub_subscriber.py
xialib_gcp-0.1.20.dist-info/LICENSE
xialib_gcp-0.1.20.dist-info/METADATA
xialib_gcp-0.1.20.dist-info/WHEEL
xialib_gcp-0.1.20.dist-info/top_level.txt
xialib_gcp-0.1.20.dist-info/RECORD
