Metadata-Version: 2.1
Name: xialib-gcp
Version: 0.1.20
Summary: X-I-A Library
Home-page: https://github.com/X-I-A/xialib-gcp
Author: Soral
Author-email: soral@x-i-a.com
License: UNKNOWN
Platform: UNKNOWN
Classifier: Programming Language :: Python :: 3
Classifier: License :: OSI Approved :: GNU General Public License v3 (GPLv3)
Classifier: Operating System :: OS Independent
Requires-Python: >=3.7
Requires-Dist: xialib
Requires-Dist: google-auth
Requires-Dist: gcsfs
Requires-Dist: google-cloud-pubsub
Requires-Dist: google-cloud-firestore
Requires-Dist: google-cloud-bigquery
